<?xml version="1.0" encoding="utf-8" ?><dwsync><file name="blank.htm" server="revivalseminars.org/wwwroot/" local="3297145080" remote="11887079672" /><file name="license.txt" server="revivalseminars.org/wwwroot/" local="3297145080" remote="11887079672" /><file name="tiny_mce.js" server="revivalseminars.org/wwwroot/" local="3297145860" remote="11887080452" /><file name="tiny_mce_popup.js" server="revivalseminars.org/wwwroot/" local="3297145860" remote="11887080452" /><file name="tiny_mce_src.js" server="revivalseminars.org/wwwroot/" local="3297145860" remote="11887080452" /><file name="blank.htm" server="acediaapparel.com/wwwroot/" local="3297145080" remote="11949978992" /><file name="license.txt" server="acediaapparel.com/wwwroot/" local="3297145080" remote="11949978992" /><file name="tiny_mce.js" server="acediaapparel.com/wwwroot/" local="3297145860" remote="11949979412" /><file name="tiny_mce_popup.js" server="acediaapparel.com/wwwroot/" local="3297145860" remote="11949979412" /><file name="tiny_mce_src.js" server="acediaapparel.com/wwwroot/" local="3297145860" remote="11949979412" /><file name="blank.htm" server="gromoregardensupply.com/wwwroot/" local="3360037250" remote="11973735152" /><file name="license.txt" server="gromoregardensupply.com/wwwroot/" local="3360037254" remote="11973735152" /><file name="tiny_mce.js" server="gromoregardensupply.com/wwwroot/" local="3360037657" remote="11973735632" /><file name="tiny_mce_popup.js" server="gromoregardensupply.com/wwwroot/" local="3360037658" remote="11973735632" /><file name="tiny_mce_src.js" server="gromoregardensupply.com/wwwroot/" local="3360037660" remote="11973735632" /></dwsync>